mipsmem.v
//------------------------------------------------
// mipsmem.sv
// As proposed by Prof. Sarah Harris
// External unified memory used by MIPS multicycle
// processor.
//------------------------------------------------

module mem(input        clk, we,
           input        [31:0] a, wd,
           output       [31:0] rd);

  reg  [31:0] RAM[63:0];

  // initialize memory with instructions
  initial
    begin
      $readmemh("memfile.dat",RAM);  // "memfile.dat" contains your
                                     //    instructions in hex
                                     // you must create this file
    end

  assign rd = RAM[a[31:2]]; // word aligned

  always @(posedge clk)
    if (we)
      RAM[a[31:2]] <= wd;
endmodule

alu.v
`include "arithmetic.v"
`include "logic.v"

module mux2_1 (logicU, arithU, sel, out);
    input [31:0] logicU, arithU;
    input sel;
    output [31:0] out;
    assign out = sel ? arithU : logicU;
endmodule

module alu (a, b, f, y, zero);
    input[31:0] a, b;
    input [2:0] f;
    output [31:0] y;
    output zero;
    wire [31:0] outLogic, outArithmetic;

    logicUnit log(a, b, f, outLogic);
    arithmetic ari(a, b, f, outArithmetic);
    mux2_1 mux(outLogic, outArithmetic, f[1], y);
    assign zero = (y == 31'b0) ? 1 : 0;
endmodule

arithmetic.v
module arithmetic (A, B, opcode, out);
    input[31:0] A, B;
    input [2:0] opcode;
    output [31:0] out;
    reg [31:0] out;

    parameter add = 3'b010, sub = 3'b110, slt = 3'b111, bne = 3'b011;

    always @ (A or B or opcode) begin
        casex (opcode)
            add: out = A + B;
            sub: out = A - B;
            bne: out = ~(A - B);
            slt: out = (A < B) ? 1 : 0;
            default: out = 31'b0;
        endcase
    end

endmodule

logic.v
module logicUnit (A, B, opcode, out);
    input[31:0] A, B;
    input [2:0] opcode;
    output [31:0] out;
    reg [31:0] out;

    parameter and_ = 3'b000, or_ = 3'b001;

    always @ (A or B or opcode) begin
        casex (opcode)
            and_: out = A & B;
            or_: out = A | B;
            default: out = 31'b0;
        endcase
    end

endmodule

mipsmulti.v
`include "mipsparts.v"
`include "alu.v"

module mips(input         clk, reset,
            output [31:0] adr, writedata,
            output        memwrite,
            input  [31:0] readdata);

  wire         zero, pcen, irwrite, regwrite,
               alusrca, iord, memtoreg, regdst;
  wire [1:0]  alusrcb, pcsrc;
  wire [2:0]  alucontrol;
  wire [5:0]  op, funct;

  controller c(clk, reset, op, funct, zero,
               pcen, memwrite, irwrite, regwrite,
               alusrca, iord, memtoreg, regdst,
               alusrcb, pcsrc, alucontrol);
  datapath dp(clk, reset,
              pcen, irwrite, regwrite,
              alusrca, iord, memtoreg, regdst,
              alusrcb, pcsrc, alucontrol,
              op, funct, zero,
              adr, writedata, readdata);
endmodule

module controller(input        clk, reset,
                  input  [5:0] op, funct,
                  input        zero,
                  output       pcen, memwrite, irwrite, regwrite,
                  output       alusrca, iord, memtoreg, regdst,
                  output [1:0] alusrcb, pcsrc,
                  output [2:0] alucontrol);

  wire [1:0] aluop;
  wire       branch, pcwrite;

  // Main Decoder and ALU Decoder subunits.
  maindec md(clk, reset, op,
             pcwrite, memwrite, irwrite, regwrite,
             alusrca, branch, iord, memtoreg, regdst,
             alusrcb, pcsrc, aluop);
  aludec  ad(funct, aluop, alucontrol);

  // Add combinational logic (i.e. an assign statement)
  // to produce the PCEn signal (pcen) from the branch,
  // zero, and pcwrite signals

  assign pcen = (branch & zero) | pcwrite;

endmodule

module maindec(input        clk, reset,
               input  [5:0] op,
               output       pcwrite, memwrite, irwrite, regwrite,
               output       alusrca, branch, iord, memtoreg, regdst,
               output [1:0] alusrcb, pcsrc,
               output [1:0] aluop);

  parameter   FETCH   = 4'b0000;  // State 0
  parameter   DECODE  = 4'b0001;  // State 1
  parameter   MEMADR  = 4'b0010;	// State 2
  parameter   MEMRD   = 4'b0011;	// State 3
  parameter   MEMWB   = 4'b0100;	// State 4
  parameter   MEMWR   = 4'b0101;	// State 5
  parameter   RTYPEEX = 4'b0110;	// State 6
  parameter   RTYPEWB = 4'b0111;	// State 7
  parameter   BEQEX   = 4'b1000;	// State 8
  parameter   ADDIEX  = 4'b1001;	// State 9
  parameter   ADDIWB  = 4'b1010;	// state 10
  parameter   JEX     = 4'b1011;	// State 11

  parameter   LW      = 6'b100011;	// Opcode for lw
  parameter   SW      = 6'b101011;	// Opcode for sw
  parameter   RTYPE   = 6'b000000;	// Opcode for R-type
  parameter   BEQ     = 6'b000100;	// Opcode for beq
  parameter   ADDI    = 6'b001000;	// Opcode for addi
  parameter   J       = 6'b000010;	// Opcode for j

  reg [3:0]  state, nextstate;
  reg [14:0] controls;

  // state register
  always @(posedge clk or posedge reset)
    if(reset) state <= FETCH;
    else state <= nextstate;

  // next state logic
  always @(*)
    case(state)
      FETCH:   nextstate <= DECODE;
      DECODE:  case(op)
                  LW:      nextstate <= MEMADR;
                  SW:      nextstate <= MEMADR;
                  RTYPE:   nextstate <= RTYPEEX;
                  BEQ:     nextstate <= BEQEX;
                  ADDI:    nextstate <= ADDIEX;
                  J:       nextstate <= JEX;
                  default: nextstate <= 4'bx; // should never happen
               endcase
      MEMADR:  case(op)
                  LW:      nextstate <= MEMRD;
                  SW:      nextstate <= MEMWR;
                  default: nextstate <= 4'bx; // should never happen
               endcase
      MEMRD:   nextstate <= MEMWB;
      MEMWB:   nextstate <= FETCH;
      MEMWR:   nextstate <= FETCH;
      RTYPEEX: nextstate <= RTYPEWB;
      RTYPEWB: nextstate <= FETCH;
      BEQEX:   nextstate <= FETCH;
      ADDIEX:  nextstate <= ADDIWB;
      ADDIWB:  nextstate <= FETCH;
      JEX:     nextstate <= FETCH;
      default: nextstate <= 4'bx; // should never happen
    endcase

  // output logic
  assign {pcwrite, memwrite, irwrite, regwrite,
          alusrca, branch, iord, memtoreg,
          regdst, alusrcb, pcsrc, aluop} = controls;

    always @ (*)
    case(state)
      FETCH:     controls <= 15'h5010;     //S0
      DECODE:    controls <= 15'h0030;     //S1
      MEMADR:    controls <= 15'h0420;     //S2
      MEMRD:     controls <= 15'h0100;     //S3
      MEMWB:     controls <= 15'h0880;     //S4
      MEMWR:     controls <= 15'h2100;     //S5
      RTYPEEX:   controls <= 15'h0402;     //S6
      RTYPEWB:   controls <= 15'h0840;     //S7
      BEQEX:     controls <= 15'h0605;     //S8
      ADDIEX:    controls <= 15'h0420;     //S9
      ADDIWB:    controls <= 15'h0800;     //S10
      JEX:       controls <= 15'h4008;     //S11
      default:   controls <= 15'hxxxx;     //should never happen
    endcase
endmodule

module aludec(input  [5:0] funct,
              input  [1:0] aluop,
              output reg [2:0] alucontrol);

  always@(*)
    case(aluop)
      2'b00: alucontrol <= 3'b010;          // add
      2'b01: alucontrol <= 3'b110;          // sub
      default: case(funct)                  // 10 RTYPE
          6'b100000: alucontrol <= 3'b010;  // ADD
          6'b100010: alucontrol <= 3'b110;  // SUB
          6'b100100: alucontrol <= 3'b000;  // AND
          6'b100101: alucontrol <= 3'b001;  // OR
          6'b101010: alucontrol <= 3'b111;  // SLT
          default:   alucontrol <= 4'bxxxx; // ???
        endcase
    endcase

endmodule

module datapath(input         clk, reset,
                input         pcen, irwrite, regwrite,
                input         alusrca, iord, memtoreg, regdst,
                input  [1:0]  alusrcb, pcsrc,
                input  [2:0]  alucontrol,
                output [5:0]  op, funct,
                output        zero,
                output [31:0] adr, writedata,
                input  [31:0] readdata);

  // Below are the internal signals of the datapath module.

  wire [4:0]  writereg;
  wire [31:0] pcnext, pc;
  wire [31:0] instr, data, srca, srcb;
  wire [31:0] a;
  wire [31:0] aluresult, aluout;
  wire [31:0] signimm;   // the sign-extended immediate
  wire [31:0] signimmsh;	// the sign-extended immediate shifted left by 2
  wire [31:0] wd3, rd1, rd2;

  // op and funct fields to controller
  assign op = instr[31:26];
  assign funct = instr[5:0];

  // datapath

  flopenr #(32) pcreg(clk, reset, pcen, pcnext, pc);
  mux2 #(32) adrmux(pc, aluout, iord, adr);

  flopenr #(32) instrreg(clk, reset, irwrite, readdata, instr);
  flopr #(32) datareg(clk, reset, readdata, data);

  mux2 #(5) regdstmux(instr[20:16], instr[15:11], regdst, writereg);

  mux2 #(32) wdmux(aluout, data, memtoreg, wd3);

  regfile regfile(clk, regwrite, instr[25:21], instr[20:16], writereg, wd3, rd1, rd2);

  flopr #(32) areg(clk, reset, rd1, a);
  flopr #(32) breg(clk, reset, rd2, writedata);

  mux2 #(32) amux(pc, a, alusrca, srca);
  signext signext(instr[15:0], signimm);
  sl2 sxsl2(signimm, signimmsh);
  mux4 #(32) srcbmux(writedata, 4, signimm, signimmsh, alusrcb, srcb);

  alu alu(srca, srcb, alucontrol, aluresult, zero);

  flopr #(32) alureg(clk, reset, aluresult, aluout);

  wire [31:0] pcjump;
  assign pcjump = {pc[31:28], instr[25:0], 2'b00};

  mux3 #(32) alumux(aluresult, aluout, pcjump, pcsrc, pcnext);


endmodule

topmulti.v
`include "mipsmulti.v"
`include "mipsmem.v"

module top(input        clk, reset,
           output       [31:0] writedata, adr,
           output       memwrite);

  wire [31:0] readdata;

  // microprocessor (control & datapath)
  mips mips(clk, reset, adr, writedata, memwrite, readdata);

  // memory
  mem mem(clk, memwrite, adr, writedata, readdata);

endmodule

mips_tb.v
`include "topmulti.v"

module testbench();

  reg        clk;
  reg        reset;

  wire [31:0] writedata, dataadr;
  wire        memwrite;

  // instantiate device to be tested
  top dut(clk, reset, writedata, dataadr, memwrite);

  // initialize test
  initial
    begin
      reset <= 1; # 10; reset <= 0;
    end

  // generate clock to sequence tests
  always
    begin
      clk <= 1; # 5; clk <= 0; # 5;
    end

  // check that 7 gets written to address 84
  always@(negedge clk)
    begin
      if(memwrite) begin
        if(dataadr == 84 & writedata == 7) begin
          $display("Simulation succeeded");
          $stop;
        end else if (dataadr != 80) begin
          $display("Simulation failed");
          $stop;
        end
      end
    end

initial begin
        $dumpfile("mips.vcd");
        $dumpvars;
end

endmodule

mipsparts.v
module regfile(input         clk,
               input         we3,
               input  [4:0]  ra1, ra2, wa3,
               input  [31:0] wd3,
               output [31:0] rd1, rd2);

  reg [31:0] rf[31:0];

  // three ported register file
  // read two ports combinationally
  // write third port on rising edge of clock
  // register 0 hardwired to 0

  always @(posedge clk)
    if (we3) rf[wa3] <= wd3;

  assign rd1 = (ra1 != 0) ? rf[ra1] : 0;
  assign rd2 = (ra2 != 0) ? rf[ra2] : 0;

endmodule

module adder(input  [31:0] a, b,
             output [31:0] y);

  assign y = a + b;
endmodule

module sl2(input  [31:0] a,
           output [31:0] y);

  // shift left by 2
  assign y = {a[29:0], 2'b00};
endmodule

module signext(input  [15:0] a,
              //  input ori,
               output [31:0] y);
  // assign y = ori ? {16'b0, a} : {{16{a[15]}}, a};
  assign y = {{16{a[15]}}, a};
endmodule

module flopr #(parameter WIDTH = 8)
              (input              clk, reset,
               input  [WIDTH-1:0] d,
               output reg [WIDTH-1:0] q);

  always @(posedge clk, posedge reset)
    if (reset) q <= 0;
    else       q <= d;
endmodule

module flopenr #(parameter WIDTH = 8)
                (input              clk, reset,
                 input              en,
                 input  [WIDTH-1:0] d,
                 output reg [WIDTH-1:0] q);

  always @(posedge clk, posedge reset)
    if      (reset) q <= 0;
    else if (en)    q <= d;
endmodule

module mux2 #(parameter WIDTH = 8)
             (input  [WIDTH-1:0] d0, d1,
              input              s,
              output [WIDTH-1:0] y);

  assign y = s ? d1 : d0;
endmodule

module mux3 #(parameter WIDTH = 8)
             (input   [WIDTH-1:0] d0, d1, d2,
              input   [1:0]       s,
              output [WIDTH-1:0] y);

  assign #1 y = s[1] ? d2 : (s[0] ? d1 : d0);
endmodule

module mux4 #(parameter WIDTH = 8)
             (input [WIDTH-1:0] d0, d1, d2, d3,
              input [1:0]       s,
              output reg [WIDTH-1:0] y);

   always @ (*)
      case(s)
         2'b00: y <= d0;
         2'b01: y <= d1;
         2'b10: y <= d2;
         2'b11: y <= d3;
      endcase
endmodule

mips.vcd
$date
	Sun Jul 19 18:41:22 2020
$end
$version
	Icarus Verilog
$end
$timescale
	1s
$end
$scope module adder $end
$var wire 32 ! a [31:0] $end
$var wire 32 " b [31:0] $end
$var wire 32 # y [31:0] $end
$upscope $end
$scope module testbench $end
$var wire 32 $ writedata [31:0] $end
$var wire 1 % memwrite $end
$var wire 32 & dataadr [31:0] $end
$var reg 1 ' clk $end
$var reg 1 ( reset $end
$scope module dut $end
$var wire 1 ' clk $end
$var wire 1 ( reset $end
$var wire 32 ) writedata [31:0] $end
$var wire 32 * readdata [31:0] $end
$var wire 1 % memwrite $end
$var wire 32 + adr [31:0] $end
$scope module mem $end
$var wire 1 ' clk $end
$var wire 32 , rd [31:0] $end
$var wire 1 % we $end
$var wire 32 - wd [31:0] $end
$var wire 32 . a [31:0] $end
$upscope $end
$scope module mips $end
$var wire 1 ' clk $end
$var wire 32 / readdata [31:0] $end
$var wire 1 ( reset $end
$var wire 1 0 zero $end
$var wire 32 1 writedata [31:0] $end
$var wire 1 2 regwrite $end
$var wire 1 3 regdst $end
$var wire 2 4 pcsrc [1:0] $end
$var wire 1 5 pcen $end
$var wire 6 6 op [5:0] $end
$var wire 1 % memwrite $end
$var wire 1 7 memtoreg $end
$var wire 1 8 irwrite $end
$var wire 1 9 iord $end
$var wire 6 : funct [5:0] $end
$var wire 2 ; alusrcb [1:0] $end
$var wire 1 < alusrca $end
$var wire 3 = alucontrol [2:0] $end
$var wire 32 > adr [31:0] $end
$scope module c $end
$var wire 1 ' clk $end
$var wire 1 5 pcen $end
$var wire 1 ( reset $end
$var wire 1 0 zero $end
$var wire 1 2 regwrite $end
$var wire 1 3 regdst $end
$var wire 1 ? pcwrite $end
$var wire 2 @ pcsrc [1:0] $end
$var wire 6 A op [5:0] $end
$var wire 1 % memwrite $end
$var wire 1 7 memtoreg $end
$var wire 1 8 irwrite $end
$var wire 1 9 iord $end
$var wire 6 B funct [5:0] $end
$var wire 1 C branch $end
$var wire 2 D alusrcb [1:0] $end
$var wire 1 < alusrca $end
$var wire 2 E aluop [1:0] $end
$var wire 3 F alucontrol [2:0] $end
$scope module ad $end
$var wire 6 G funct [5:0] $end
$var wire 2 H aluop [1:0] $end
$var reg 3 I alucontrol [2:0] $end
$upscope $end
$scope module md $end
$var wire 1 ' clk $end
$var wire 1 ( reset $end
$var wire 1 2 regwrite $end
$var wire 1 3 regdst $end
$var wire 1 ? pcwrite $end
$var wire 2 J pcsrc [1:0] $end
$var wire 6 K op [5:0] $end
$var wire 1 % memwrite $end
$var wire 1 7 memtoreg $end
$var wire 1 8 irwrite $end
$var wire 1 9 iord $end
$var wire 1 C branch $end
$var wire 2 L alusrcb [1:0] $end
$var wire 1 < alusrca $end
$var wire 2 M aluop [1:0] $end
$var reg 15 N controls [14:0] $end
$var reg 4 O nextstate [3:0] $end
$var reg 4 P state [3:0] $end
$upscope $end
$upscope $end
$scope module dp $end
$var wire 3 Q alucontrol [2:0] $end
$var wire 1 < alusrca $end
$var wire 2 R alusrcb [1:0] $end
$var wire 1 ' clk $end
$var wire 1 9 iord $end
$var wire 1 8 irwrite $end
$var wire 1 7 memtoreg $end
$var wire 1 5 pcen $end
$var wire 2 S pcsrc [1:0] $end
$var wire 32 T readdata [31:0] $end
$var wire 1 3 regdst $end
$var wire 1 2 regwrite $end
$var wire 1 ( reset $end
$var wire 1 0 zero $end
$var wire 5 U writereg [4:0] $end
$var wire 32 V writedata [31:0] $end
$var wire 32 W wd3 [31:0] $end
$var wire 32 X srcb [31:0] $end
$var wire 32 Y srca [31:0] $end
$var wire 32 Z signimmsh [31:0] $end
$var wire 32 [ signimm [31:0] $end
$var wire 32 \ rd2 [31:0] $end
$var wire 32 ] rd1 [31:0] $end
$var wire 32 ^ pcnext [31:0] $end
$var wire 32 _ pcjump [31:0] $end
$var wire 32 ` pc [31:0] $end
$var wire 6 a op [5:0] $end
$var wire 32 b instr [31:0] $end
$var wire 6 c funct [5:0] $end
$var wire 32 d data [31:0] $end
$var wire 32 e aluresult [31:0] $end
$var wire 32 f aluout [31:0] $end
$var wire 32 g adr [31:0] $end
$var wire 32 h a [31:0] $end
$scope module adrmux $end
$var wire 1 9 s $end
$var wire 32 i y [31:0] $end
$var wire 32 j d1 [31:0] $end
$var wire 32 k d0 [31:0] $end
$upscope $end
$scope module alu $end
$var wire 3 l f [2:0] $end
$var wire 1 0 zero $end
$var wire 32 m y [31:0] $end
$var wire 32 n outLogic [31:0] $end
$var wire 32 o outArithmetic [31:0] $end
$var wire 32 p b [31:0] $end
$var wire 32 q a [31:0] $end
$scope module ari $end
$var wire 3 r opcode [2:0] $end
$var wire 32 s B [31:0] $end
$var wire 32 t A [31:0] $end
$var reg 32 u out [31:0] $end
$upscope $end
$scope module log $end
$var wire 3 v opcode [2:0] $end
$var wire 32 w B [31:0] $end
$var wire 32 x A [31:0] $end
$var reg 32 y out [31:0] $end
$upscope $end
$scope module mux $end
$var wire 32 z arithU [31:0] $end
$var wire 32 { logicU [31:0] $end
$var wire 1 | sel $end
$var wire 32 } out [31:0] $end
$upscope $end
$upscope $end
$scope module alumux $end
$var wire 32 ~ d0 [31:0] $end
$var wire 32 !" d2 [31:0] $end
$var wire 2 "" s [1:0] $end
$var wire 32 #" y [31:0] $end
$var wire 32 $" d1 [31:0] $end
$upscope $end
$scope module alureg $end
$var wire 1 ' clk $end
$var wire 32 %" d [31:0] $end
$var wire 1 ( reset $end
$var reg 32 &" q [31:0] $end
$upscope $end
$scope module amux $end
$var wire 1 < s $end
$var wire 32 '" y [31:0] $end
$var wire 32 (" d1 [31:0] $end
$var wire 32 )" d0 [31:0] $end
$upscope $end
$scope module areg $end
$var wire 1 ' clk $end
$var wire 1 ( reset $end
$var wire 32 *" d [31:0] $end
$var reg 32 +" q [31:0] $end
$upscope $end
$scope module breg $end
$var wire 1 ' clk $end
$var wire 1 ( reset $end
$var wire 32 ," d [31:0] $end
$var reg 32 -" q [31:0] $end
$upscope $end
$scope module datareg $end
$var wire 1 ' clk $end
$var wire 32 ." d [31:0] $end
$var wire 1 ( reset $end
$var reg 32 /" q [31:0] $end
$upscope $end
$scope module instrreg $end
$var wire 1 ' clk $end
$var wire 32 0" d [31:0] $end
$var wire 1 8 en $end
$var wire 1 ( reset $end
$var reg 32 1" q [31:0] $end
$upscope $end
$scope module pcreg $end
$var wire 1 ' clk $end
$var wire 32 2" d [31:0] $end
$var wire 1 5 en $end
$var wire 1 ( reset $end
$var reg 32 3" q [31:0] $end
$upscope $end
$scope module regdstmux $end
$var wire 5 4" d0 [4:0] $end
$var wire 5 5" d1 [4:0] $end
$var wire 1 3 s $end
$var wire 5 6" y [4:0] $end
$upscope $end
$scope module regfile $end
$var wire 1 ' clk $end
$var wire 5 7" ra1 [4:0] $end
$var wire 5 8" ra2 [4:0] $end
$var wire 5 9" wa3 [4:0] $end
$var wire 1 2 we3 $end
$var wire 32 :" wd3 [31:0] $end
$var wire 32 ;" rd2 [31:0] $end
$var wire 32 <" rd1 [31:0] $end
$upscope $end
$scope module signext $end
$var wire 16 =" a [15:0] $end
$var wire 32 >" y [31:0] $end
$upscope $end
$scope module srcbmux $end
$var wire 32 ?" d0 [31:0] $end
$var wire 32 @" d1 [31:0] $end
$var wire 32 A" d2 [31:0] $end
$var wire 2 B" s [1:0] $end
$var wire 32 C" d3 [31:0] $end
$var reg 32 D" y [31:0] $end
$upscope $end
$scope module sxsl2 $end
$var wire 32 E" a [31:0] $end
$var wire 32 F" y [31:0] $end
$upscope $end
$scope module wdmux $end
$var wire 32 G" d0 [31:0] $end
$var wire 32 H" d1 [31:0] $end
$var wire 1 7 s $end
$var wire 32 I" y [31:0] $end
$upscope $end
$upscope $end
$upscope $end
$upscope $end
$upscope $end
$enddefinitions $end
#0
$dumpvars
b0 I"
b0 H"
b0 G"
b0 F"
b0 E"
b100 D"
b0 C"
b1 B"
b0 A"
b100 @"
b0 ?"
b0 >"
b0 ="
b0 <"
b0 ;"
b0 :"
b0 9"
b0 8"
b0 7"
b0 6"
b0 5"
b0 4"
b0 3"
bx 2"
b0 1"
b100000000000100000000000000101 0"
b0 /"
b100000000000100000000000000101 ."
b0 -"
b0 ,"
b0 +"
b0 *"
b0 )"
b0 ("
b0 '"
b0 &"
b100 %"
b0 $"
bx #"
b0 ""
b0 !"
b100 ~
b100 }
1|
b0 {
b100 z
b0 y
b0 x
b100 w
b10 v
b100 u
b0 t
b100 s
b10 r
b0 q
b100 p
b100 o
b0 n
b100 m
b10 l
b0 k
b0 j
b0 i
b0 h
b0 g
b0 f
b100 e
b0 d
b0 c
b0 b
b0 a
b0 `
b0 _
bx ^
b0 ]
b0 \
b0 [
b0 Z
b0 Y
b100 X
b0 W
b0 V
b0 U
b100000000000100000000000000101 T
b0 S
b1 R
b10 Q
b0 P
b1 O
b101000000010000 N
b0 M
b1 L
b0 K
b0 J
b10 I
b0 H
b0 G
b10 F
b0 E
b1 D
0C
b0 B
b0 A
b0 @
1?
b0 >
b10 =
0<
b1 ;
b0 :
09
18
07
b0 6
15
b0 4
03
02
b0 1
00
b100000000000100000000000000101 /
b0 .
b0 -
b100000000000100000000000000101 ,
b0 +
b100000000000100000000000000101 *
b0 )
1(
1'
b0 &
0%
b0 $
bx #
bz "
bz !
$end
#1
b100 ^
b100 #"
b100 2"
#5
0'
#10
b10100 X
b10100 p
b10100 s
b10100 w
b10100 D"
05
0?
08
b11 ;
b11 D
b11 L
b11 R
b11 B"
b110000 N
b1001 O
b11000 e
b11000 m
b11000 }
b11000 ~
b11000 %"
b10100 Z
b10100 C"
b10100 F"
bx \
bx ,"
bx ;"
b10 U
b10 6"
b10 9"
b11000 o
b11000 u
b11000 z
b100000000000110000000000001100 *
b100000000000110000000000001100 ,
b100000000000110000000000001100 /
b100000000000110000000000001100 T
b100000000000110000000000001100 ."
b100000000000110000000000001100 0"
b100 W
b100 :"
b100 I"
b10000000000000010100 _
b10000000000000010100 !"
b101 [
b101 >"
b101 A"
b101 E"
b101 ="
b10 8"
b10 4"
b101 :
b101 B
b101 G
b101 c
b1000 6
b1000 A
b1000 K
b1000 a
b100 Y
b100 q
b100 t
b100 x
b100 '"
b100 &
b100 +
b100 .
b100 >
b100 g
b100 i
b100 f
b100 j
b100 $"
b100 &"
b100 G"
b100000000000100000000000000101 d
b100000000000100000000000000101 /"
b100000000000100000000000000101 H"
b100000000000100000000000000101 b
b100000000000100000000000000101 1"
b100 `
b100 k
b100 )"
b100 3"
b1 P
1'
0(
#11
b11000 ^
b11000 #"
b11000 2"
#15
0'
#20
b101 X
b101 p
b101 s
b101 w
b101 D"
b101 e
b101 m
b101 }
b101 ~
b101 %"
b101 o
b101 u
b101 z
b0 Y
b0 q
b0 t
b0 x
b0 '"
1<
b10 ;
b10 D
b10 L
b10 R
b10 B"
b10000100000 N
b1010 O
b11000 W
b11000 :"
b11000 I"
b1001 P
b100000000000110000000000001100 d
b100000000000110000000000001100 /"
b100000000000110000000000001100 H"
bx $
bx )
bx -
bx 1
bx V
bx -"
bx ?"
b11000 f
b11000 j
b11000 $"
b11000 &"
b11000 G"
1'
#21
b101 ^
b101 #"
b101 2"
#25
0'
#30
x0
bx X
bx p
bx s
bx w
bx D"
bx e
bx m
bx }
bx ~
bx %"
bx o
bx u
bx z
b100 Y
b100 q
b100 t
b100 x
b100 '"
12
0<
b0 ;
b0 D
b0 L
b0 R
b0 B"
b100000000000 N
b0 O
b101 W
b101 :"
b101 I"
b101 f
b101 j
b101 $"
b101 &"
b101 G"
b1010 P
1'
#31
bx ^
bx #"
bx 2"
#35
0'
#40
00
b1000 e
b1000 m
b1000 }
b1000 ~
b1000 %"
b1000 o
b1000 u
b1000 z
b100 X
b100 p
b100 s
b100 w
b100 D"
15
1?
18
02
b1 ;
b1 D
b1 L
b1 R
b1 B"
b101000000010000 N
b1 O
b101 \
b101 ,"
b101 ;"
bx W
bx :"
bx I"
b0 P
bx f
bx j
bx $"
bx &"
bx G"
1'
#41
b1000 ^
b1000 #"
b1000 2"
#45
0'
#50
b110000 X
b110000 p
b110000 s
b110000 w
b110000 D"
05
0?
08
b11 ;
b11 D
b11 L
b11 R
b11 B"
b110000 N
b1001 O
b111000 e
b111000 m
b111000 }
b111000 ~
b111000 %"
b110000 Z
b110000 C"
b110000 F"
bx \
bx ,"
bx ;"
b11 U
b11 6"
b11 9"
b111000 o
b111000 u
b111000 z
b100000011001111111111111110111 *
b100000011001111111111111110111 ,
b100000011001111111111111110111 /
b100000011001111111111111110111 T
b100000011001111111111111110111 ."
b100000011001111111111111110111 0"
b1000 W
b1000 :"
b1000 I"
b11000000000000110000 _
b11000000000000110000 !"
b1100 [
b1100 >"
b1100 A"
b1100 E"
b1100 ="
b11 8"
b11 4"
b1100 :
b1100 B
b1100 G
b1100 c
b1000 Y
b1000 q
b1000 t
b1000 x
b1000 '"
b1000 &
b1000 +
b1000 .
b1000 >
b1000 g
b1000 i
b1000 f
b1000 j
b1000 $"
b1000 &"
b1000 G"
b101 $
b101 )
b101 -
b101 1
b101 V
b101 -"
b101 ?"
b100000000000110000000000001100 b
b100000000000110000000000001100 1"
b1000 `
b1000 k
b1000 )"
b1000 3"
b1 P
1'
#51
b111000 ^
b111000 #"
b111000 2"
#55
0'
#60
b1100 X
b1100 p
b1100 s
b1100 w
b1100 D"
b1100 e
b1100 m
b1100 }
b1100 ~
b1100 %"
b1100 o
b1100 u
b1100 z
b0 Y
b0 q
b0 t
b0 x
b0 '"
1<
b10 ;
b10 D
b10 L
b10 R
b10 B"
b10000100000 N
b1010 O
b111000 W
b111000 :"
b111000 I"
b1001 P
b100000011001111111111111110111 d
b100000011001111111111111110111 /"
b100000011001111111111111110111 H"
bx $
bx )
bx -
bx 1
bx V
bx -"
bx ?"
b111000 f
b111000 j
b111000 $"
b111000 &"
b111000 G"
1'
#61
b1100 ^
b1100 #"
b1100 2"
#65
0'
#70
x0
bx X
bx p
bx s
bx w
bx D"
bx e
bx m
bx }
bx ~
bx %"
bx o
bx u
bx z
b1000 Y
b1000 q
b1000 t
b1000 x
b1000 '"
12
0<
b0 ;
b0 D
b0 L
b0 R
b0 B"
b100000000000 N
b0 O
b1100 W
b1100 :"
b1100 I"
b1100 f
b1100 j
b1100 $"
b1100 &"
b1100 G"
b1010 P
1'
#71
bx ^
bx #"
bx 2"
#75
0'
#80
00
b1100 e
b1100 m
b1100 }
b1100 ~
b1100 %"
b1100 o
b1100 u
b1100 z
b100 X
b100 p
b100 s
b100 w
b100 D"
15
1?
18
02
b1 ;
b1 D
b1 L
b1 R
b1 B"
b101000000010000 N
b1 O
b1100 \
b1100 ,"
b1100 ;"
bx W
bx :"
bx I"
b0 P
bx f
bx j
bx $"
bx &"
bx G"
1'
#81
b1100 ^
b1100 #"
b1100 2"
#85
0'
#90
b11111111111111111111111111011100 X
b11111111111111111111111111011100 p
b11111111111111111111111111011100 s
b11111111111111111111111111011100 w
b11111111111111111111111111011100 D"
05
0?
08
b11 ;
b11 D
b11 L
b11 R
b11 B"
b110000 N
b1001 O
b11111111111111111111111111101000 e
b11111111111111111111111111101000 m
b11111111111111111111111111101000 }
b11111111111111111111111111101000 ~
b11111111111111111111111111101000 %"
b11111111111111111111111111011100 Z
b11111111111111111111111111011100 C"
b11111111111111111111111111011100 F"
bx \
bx ,"
bx ;"
b1100 ]
b1100 *"
b1100 <"
b111 U
b111 6"
b111 9"
b11111111111111111111111111101000 o
b11111111111111111111111111101000 u
b11111111111111111111111111101000 z
b111000100010000000100101 *
b111000100010000000100101 ,
b111000100010000000100101 /
b111000100010000000100101 T
b111000100010000000100101 ."
b111000100010000000100101 0"
b1100 W
b1100 :"
b1100 I"
b1100111111111111111011100 _
b1100111111111111111011100 !"
b11111111111111111111111111110111 [
b11111111111111111111111111110111 >"
b11111111111111111111111111110111 A"
b11111111111111111111111111110111 E"
b1111111111110111 ="
b111 8"
b11 7"
b11111 5"
b111 4"
b110111 :
b110111 B
b110111 G
b110111 c
b1100 Y
b1100 q
b1100 t
b1100 x
b1100 '"
b1100 &
b1100 +
b1100 .
b1100 >
b1100 g
b1100 i
b1100 f
b1100 j
b1100 $"
b1100 &"
b1100 G"
b1100 $
b1100 )
b1100 -
b1100 1
b1100 V
b1100 -"
b1100 ?"
b100000011001111111111111110111 b
b100000011001111111111111110111 1"
b1100 `
b1100 k
b1100 )"
b1100 3"
b1 P
1'
#91
b11111111111111111111111111101000 ^
b11111111111111111111111111101000 #"
b11111111111111111111111111101000 2"
#95
0'
#100
b11 e
b11 m
b11 }
b11 ~
b11 %"
b11 o
b11 u
b11 z
b11111111111111111111111111110111 X
b11111111111111111111111111110111 p
b11111111111111111111111111110111 s
b11111111111111111111111111110111 w
b11111111111111111111111111110111 D"
1<
b10 ;
b10 D
b10 L
b10 R
b10 B"
b10000100000 N
b1010 O
b11111111111111111111111111101000 W
b11111111111111111111111111101000 :"
b11111111111111111111111111101000 I"
b1001 P
b111000100010000000100101 d
b111000100010000000100101 /"
b111000100010000000100101 H"
b1100 h
b1100 ("
b1100 +"
bx $
bx )
bx -
bx 1
bx V
bx -"
bx ?"
b11111111111111111111111111101000 f
b11111111111111111111111111101000 j
b11111111111111111111111111101000 $"
b11111111111111111111111111101000 &"
b11111111111111111111111111101000 G"
1'
#101
b11 ^
b11 #"
b11 2"
#105
0'
#110
x0
bx e
bx m
bx }
bx ~
bx %"
bx o
bx u
bx z
bx X
bx p
bx s
bx w
bx D"
12
0<
b0 ;
b0 D
b0 L
b0 R
b0 B"
b100000000000 N
b0 O
b11 W
b11 :"
b11 I"
b11 f
b11 j
b11 $"
b11 &"
b11 G"
b1010 P
1'
#111
bx ^
bx #"
bx 2"
#115
0'
